poetry_arbitrary_version_plugin/__init__.py
poetry_arbitrary_version_plugin/plugin.py
poetry_arbitrary_version_plugin-0.9.2.dist-info/entry_points.txt
poetry_arbitrary_version_plugin-0.9.2.dist-info/LICENSE
poetry_arbitrary_version_plugin-0.9.2.dist-info/WHEEL
poetry_arbitrary_version_plugin-0.9.2.dist-info/METADATA
poetry_arbitrary_version_plugin-0.9.2.dist-info/RECORD
